{
  "$id": "https://vng.opencatalogi.nl/schemas/fieldvalidationerror.schema.json",
  "$schema": "https://docs.commongateway.nl/schemas/Entity.schema.json",
  "version": "0.1",
  "title": "FieldValidationError",
  "type": "object",
  "description": "Formaat van validatiefouten.",
  "properties": {
    "name": {
      "type": "string",
      "description": "Naam van het veld met ongeldige gegevens",
      "title": "name"
    },
    "code": {
      "type": "string",
      "description": "Systeemcode die het type fout aangeeft",
      "title": "code"
    },
    "reason": {
      "type": "string",
      "description": "Uitleg wat er precies fout is met de gegevens",
      "title": "reason"
    }
  },
  "required": [
    "code",
    "name",
    "reason"
  ]
}
